bopforge/__init__.py
bopforge/utils.py
bopforge/continuous_pipeline/__init__.py
bopforge/continuous_pipeline/__main__.py
bopforge/continuous_pipeline/functions.py
bopforge/dichotomous_pipeline/__init__.py
bopforge/dichotomous_pipeline/__main__.py
bopforge/dichotomous_pipeline/functions.py
bopforge-0.0.6.dist-info/LICENSE
bopforge-0.0.6.dist-info/METADATA
bopforge-0.0.6.dist-info/WHEEL
bopforge-0.0.6.dist-info/entry_points.txt
bopforge-0.0.6.dist-info/top_level.txt
bopforge-0.0.6.dist-info/RECORD
