Metadata-Version: 2.1
Name: bopforge
Version: 0.0.6
Summary: Pipelines for Burden of Proof (BoP) analyses
Author-email: IHME Math Sciences <ihme.math.sciences@gmail.com>
License: BSD 2-Clause License
Project-URL: github, https://github.com/ihmeuw-msca/bopforge
Requires-Python: >=3.10
License-File: LICENSE
Requires-Dist: numpy
Requires-Dist: scipy
Requires-Dist: pandas
Requires-Dist: matplotlib
Requires-Dist: mrtool ==0.1.4
Requires-Dist: pplkit
Provides-Extra: docs
Requires-Dist: sphinx ; extra == 'docs'
Requires-Dist: sphinx-autodoc-typehints ; extra == 'docs'
Requires-Dist: furo ; extra == 'docs'
Provides-Extra: test
Requires-Dist: pytest ; extra == 'test'
